icpp/__init__.py
icpp/__main__.py
icpp/commands_build_native.py
icpp/commands_build_wasm.py
icpp/commands_get.py
icpp/commands_init.py
icpp/commands_install_wasi_sdk.py
icpp/config_default.py
icpp/conftest_base.py
icpp/decorators.py
icpp/icpp_toml.py
icpp/options_build.py
icpp/options_main.py
icpp/pro.py
icpp/py.typed
icpp/run_shell_cmd.py
icpp/smoketest.py
icpp/version.py
icpp/version_wasi_sdk.py
icpp/canisters/greet/README.md
icpp/canisters/greet/demo.ps1
icpp/canisters/greet/demo.sh
icpp/canisters/greet/dfx.json
icpp/canisters/greet/icpp.toml
icpp/canisters/greet/native/main.cpp
icpp/canisters/greet/native/main.h
icpp/canisters/greet/src/greet.cpp
icpp/canisters/greet/src/greet.did
icpp/canisters/greet/src/greet.h
icpp/canisters/greet/test/__init__.py
icpp/canisters/greet/test/conftest.py
icpp/canisters/greet/test/test_apis.py
icpp/ic/canister/canister.h
icpp/ic/canister/canister_base.cpp
icpp/ic/canister/canister_base.h
icpp/ic/canister/canister_cleanup_callback.cpp
icpp/ic/canister/canister_cleanup_callback.h
icpp/ic/canister/canister_global_timer.cpp
icpp/ic/canister/canister_global_timer.h
icpp/ic/canister/canister_heartbeat.cpp
icpp/ic/canister/canister_heartbeat.h
icpp/ic/canister/canister_init.cpp
icpp/ic/canister/canister_init.h
icpp/ic/canister/canister_inspect_message.cpp
icpp/ic/canister/canister_inspect_message.h
icpp/ic/canister/canister_post_upgrade.cpp
icpp/ic/canister/canister_post_upgrade.h
icpp/ic/canister/canister_pre_upgrade.cpp
icpp/ic/canister/canister_pre_upgrade.h
icpp/ic/canister/canister_query.cpp
icpp/ic/canister/canister_query.h
icpp/ic/canister/canister_reject_callback.cpp
icpp/ic/canister/canister_reject_callback.h
icpp/ic/canister/canister_reply_callback.cpp
icpp/ic/canister/canister_reply_callback.h
icpp/ic/canister/canister_start.cpp
icpp/ic/canister/canister_start.h
icpp/ic/canister/canister_update.cpp
icpp/ic/canister/canister_update.h
icpp/ic/ic0/ic0.h
icpp/ic/ic0mock/global.h
icpp/ic/ic0mock/ic0.cpp
icpp/ic/ic0mock/ic0.h
icpp_free-3.1.1.dist-info/LICENSE
icpp_free-3.1.1.dist-info/METADATA
icpp_free-3.1.1.dist-info/WHEEL
icpp_free-3.1.1.dist-info/entry_points.txt
icpp_free-3.1.1.dist-info/top_level.txt
icpp_free-3.1.1.dist-info/RECORD
